setup.py
src/dctmpy/__init__.py
src/dctmpy/docbaseclient.py
src/dctmpy/docbrokerclient.py
src/dctmpy/identity.py
src/dctmpy.egg-info/PKG-INFO
src/dctmpy.egg-info/SOURCES.txt
src/dctmpy.egg-info/dependency_links.txt
src/dctmpy.egg-info/entry_points.txt
src/dctmpy.egg-info/not-zip-safe
src/dctmpy.egg-info/requires.txt
src/dctmpy.egg-info/top_level.txt
src/dctmpy/crypto/__init__.py
src/dctmpy/exceptions/__init__.py
src/dctmpy/nagios/__init__.py
src/dctmpy/nagios/check_docbase.py
src/dctmpy/nagios/check_docbroker.py
src/dctmpy/net/__init__.py
src/dctmpy/net/netwise.py
src/dctmpy/net/request.py
src/dctmpy/net/response.py
src/dctmpy/obj/__init__.py
src/dctmpy/obj/attrinfo.py
src/dctmpy/obj/attrvalue.py
src/dctmpy/obj/collection.py
src/dctmpy/obj/docbroker.py
src/dctmpy/obj/entrypoints.py
src/dctmpy/obj/persistent.py
src/dctmpy/obj/type.py
src/dctmpy/obj/typecache.py
src/dctmpy/obj/typedobject.py
src/dctmpy/obj/typeinfo.py
src/dctmpy/rpc/__init__.py
src/dctmpy/rpc/messages.py
src/dctmpy/rpc/rpccommands.py