Metadata-Version: 1.1
Name: dctmpy
Version: 0.3.3
Summary: Python bindings for Documentum
Home-page: https://github.com/andreybpanfilov/dctmpy
Author: Andrey B. Panfilov
Author-email: andrew@panfilov.tel
License: ZPL-2.1
Platform: UNKNOWN
Classifier: Development Status :: 4 - Beta
Classifier: Environment :: Plugins
Classifier: Intended Audience :: Developers
Classifier: Intended Audience :: System Administrators
Classifier: License :: OSI Approved :: Zope Public License
Classifier: Operating System :: Microsoft :: Windows
Classifier: Operating System :: POSIX
Classifier: Programming Language :: Python :: 2.6
Classifier: Programming Language :: Python :: 2.7
Classifier: Topic :: Software Development :: Libraries :: Python Modules
Classifier: Topic :: System :: Monitoring
